{"commands":{"$perms":{"level":-1,"perms":{"roles":[],"users":["i170219703363567616"]}},"$cointoss":{"level":0,"perms":{"roles":[],"users":[]}},"$ment add":{"level":0,"perms":{"roles":[],"users":["e184030502070517761"]}},"$ment remove":{"level":0,"perms":{"roles":[],"users":["e184030502070517761"]}},"$ment":{"level":0,"perms":{"roles":[],"users":["e184030502070517761"]}}},"custcommands":{},"responses":{" $ment":{"level":0,"perms":{"roles":[],"users":["e184030502070517761"]}}},"levels":{"170219703363567616":-1,"185192156489580544":0,"184030502070517761":0}}